Workbook

Sheet Transaction
B2: Mini M&A Model- Tata Consumer Product & Britannia
B3: Hypothetical transaction | Base case uses 25% premium, 70% debt / 30% stock, normalized adjusted earnings.
B5: Transaction Assumptions
B6: TATA Consumer reference price | D6: 1014 | F6: Screeener Current Price (17 Sep, 2026)
B7: Britannia reference price | D7: 5019 | F7: Screeener Current Price (18 Sep, 2026)
B8: Premium | D8: 0.25 | F8: User-directed modeling range: 20%-30%; base case 25%
B9: Debt Financing % | D9: 0.7 | F9: User-directed modeling range: 60%-80%; base case 70%
B10: Stock Financing | D10: 0.3
B11: Tax Rate | D11: 0.2464 | F11: TATA Consumer FY2026 guidance tax rate
B12: New debt interest rate | D12: 0.05 | F12: Model assumption
B13: Annual pre-tax cost synergy | D13: 800 | F13: Model assumption; sensitivity driver
B14: One time transaction | D14: 200 | F14: Model assumption; excluded from recurring EPS
B15: Incremental PPA amortization / D&A | D15: 0 | F15: Simplified mini-model assumption
B17: Transaction Output
B18: Britannia shares outstanding | D18: =Target!D10 -> 24.08
B19: Offer price per Britannia shares | D19: =D7*(1+D8) -> 6273.75
B20: Equity purchase price | D20: =D18*D19 -> 151071.9
B21: Debt Consideration | D21: =D20*D9 -> 105750.33
B22: Stock Consideration | D22: =D20*D10 -> 45321.57
B23: New TATA Consumer share issued | D23: =D22/D6 -> 44.695828
B24: Implied equity purchase premium | D24: =D20-(Target!D10*Transaction!D7) -> 30214.38
B26: Model Convention
B27: Currency - INR
B28: Earnings basis - Adjusted earnings in base case
B29: Transaction status - Hypothetical
B30: Timing - Assumes full year recurring pro forma impact, no purchase accounting step-up model.

Sheet Acquirer
B2: Acquirer - TATA Consumer Product
B5: Acquirer Public Data
B6: Fiscal year sales | D6: 20290
B7: Net Earnings | D7: 1542.3
B8: Adjusted Net Earnings | D8: 1552
B9: Diluted shares used for FY25 EPS | D9: 99.01
B10: Shares Outstanding | D10: 98.95
B11: Share Price | D11: 1014.45
B12: Net Total Debt | D12: 2978
B13: Adjusted EBITDA | D13: 2815
B15: Calculated Metrics
B16: Adjusted EPS | D16: =D8/D10 -> 15.684689
B17: EPS | D17: =D7/D10 -> 15.58666
B18: Market Capitalization | D18: =D10*D11 -> 100379.83
B19: Net Debt / Adjusted EBITDA | D19: =D12/D13 -> 1.0579041

Sheet Target
B2: Target - Britannia Industries Ltd.
B5: Target Public Data
B6: Fiscal year sales | D6: 19151.59
B7: Net Earnings | D7: 2533.49
B8: Adjusted Net Earnings | D8: 2440.9
B9: Diluted shares used for FY25 EPS | D9: 24.09
B10: Shares Outstanding | D10: 24.08
B11: Share Price | D11: 5019
B12: Net Total Debt | D12: 1127.78
B13: Adjusted EBITDA | D13: 3547.3
B14: Cash & Cash Equivalents | D14: 220
B16: Calculated Metrics
B17: Adjusted EPS | D17: =D8/D10 -> 101.36628
B18: EPS | D18: =D7/D10 -> 105.21138
B19: Market Capitalization | D19: =D11*D10 -> 120857.52
B20: Net Debt | D20: =D12 -> 1127.78

Sheet Purchase
B2: Purchase Consideration
B5: Purchase Price
B6: Britannia reference price | D6: =Transaction!D7 -> 5019
B7: Premium | D7: =Transaction!D8 -> 0.25
B8: Offer price per Britannia shares | D8: =Transaction!D19 -> 6273.75
B9: Shares Outstanding | D9: =Target!D10 -> 24.08
B10: Equity purchase price | D10: =D8*D9 -> 151071.9
B11: Premium value paid | D11: =D10-(D6*D9) -> 30214.38
B12: Target net debt assumed | D12: =Target!D20 -> 1127.78
B13: Implied enterprise value | D13: =D10+D12 -> 152199.68
B16: Consideration Mix
B17: Debt % | D17: =Transaction!D9 -> 0.7
B18: Stock % | D18: =Transaction!D10 -> 0.3
B19: Debt Consideration | D19: =D10*D17 -> 105750.33
B20: Stock Consideration | D20: =D10*D18 -> 45321.57
B21: TATA Consumer share price | D21: =Acquirer!D11 -> 1014.45
B22: TATA Consumer share issued | D22: =D20/D21 -> 44.676002
B23: Chech: Consideration = Equity Value | D23: =D19+D20-D10 -> 0

Sheet Financing
B2: Financing
B5: Debt Financing
B6: New acquisition debt | D6: =Purchase!D19 -> 105750.33
B7: Interest rate | D7: =Transaction!D12 -> 0.05
B8: Annual cash interest expenses | D8: =D6*D7 -> 5287.5165
B9: After-tax interest expense | D9: =D8*(1-Transaction!D11) -> 3984.6724
B12: Leverage Check
B13: TATA Consumer existing net total debt | D13: =Acquirer!D12 -> 2978
B14: Pro forma net debt before target debt assumption | D14: =D13+D6 -> 108728.33
B15: Target net debt assumed | D15: =Target!D20 -> 1127.78
B16: Pro forma net debt (including tax debt) | D16: =D14+D15 -> 109856.11
B17: TATA Consumer adjusted EBITDA | D17: =Acquirer!D13 -> 2815
B18: Britannia adjusted EBITDA | D18: =Target!D13 -> 3547.3
B19: Combined adjusted EBITDA before synergy | D19: =D17+D18 -> 6362.3
B20: Pro forma net leverage (including target debt) | D20: =D16/D19 -> 17.266729

Sheet Adjustment
B2: Transaction Adjustment
B4: Recurring Transaction Adjustment
B5: Target adjusted net income
B6: Pre-tax cost synergy | D6: =Transaction!D13 -> 800
B7: After-tax cost synergy | D7: =D6*(1-Transaction!D11) -> 602.88
B8: After-tax incremental financing cost | D8: =-Financing!D9 -> -3984.6724
B9: Incremental PPA amortization / D&A | D9: =Transaction!D15 -> 0
B10: Recurring Transaction Adjustment | D10: =SUM(D5:D9) -> -2581.7924
B15: Non-recurring items: Not included in recurring EPS
B16: One time transaction | D16: =Transaction!D14 -> 200
B17: After-tax one-time cost | D17: =D16*(1-Transaction!D11) -> 150.72

Sheet Pro Forma
B2: Pro Forma Income Statement
B5: Normalised / Adjusted Basis
B6: INR except per-share data | D6: TATA Consumer Product | E6: Britannia | F6: Adjustment | G6: Pro Forma
B7: Sales | D7: =Acquirer!D6 -> 20290 | E7: =Target!D6 -> 19151.59 | F7: 0 | G7: =SUM(D7:F7) -> 39441.59
B8: Adjusted net earning | D8: =Acquirer!D8 -> 1552 | E8: =Target!D8 -> 2440.9 | F8: =Adjustment!D10 -> -2581.7924 | G8: =SUM(D8:F8) -> 1411.1076
B9: Diluted shares / Shares outstanding | D9: =Acquirer!D10 -> 98.95 | E9: =Target!D10 -> 24.08 | F9: =Purchase!D22 -> 44.676002 | G9: =D9+F9 -> 143.626
B10: Adjusted EPS | D10: =Acquirer!D16 -> 15.684689 | E10: =Target!D17 -> 101.36628 | F10: 0 | G10: =G8/G9 -> 9.8248754
B11: EPS Accretion / (Dilution) | G11: =(G10/Acquirer!D17-1) -> -0.36966127
B12: EPS change | G12: =G10-Acquirer!D17 -> -5.7617846

Sheet Accretion-Dilution
B2: Accretion / Dilution Analysis
B5: Base Case Result
B6: TATA Consumer adjusted EPS | D6: =Acquirer!D16 -> 15.684689
B7: Pro forma adjusted EPS | D7: ='Pro Forma'!G10 -> 9.8248754
B8: EPS Accretion / (Dilution) | D8: ='Pro Forma'!G11 -> -0.36966127
B9: EPS Increase / (Decrease) | D9: ='Pro Forma'!G12 -> -5.7617846
B10: Result | D10: =IF(D8>0,"Accretion","Dilution") -> Dilution
